sailplay.py
sailplay-0.2.0.dist-info/DESCRIPTION.rst
sailplay-0.2.0.dist-info/METADATA
sailplay-0.2.0.dist-info/metadata.json
sailplay-0.2.0.dist-info/RECORD
sailplay-0.2.0.dist-info/top_level.txt
sailplay-0.2.0.dist-info/WHEEL
